[{"DownloadCount":2439,"UnixTimestamp":1665521472},{"DownloadCount":2435,"UnixTimestamp":1665439118},{"DownloadCount":2430,"UnixTimestamp":1665349250},{"DownloadCount":2426,"UnixTimestamp":1665333388},{"DownloadCount":2420,"UnixTimestamp":1665267782},{"DownloadCount":2416,"UnixTimestamp":1665205612},{"DownloadCount":2412,"UnixTimestamp":1665057404},{"DownloadCount":2408,"UnixTimestamp":1664965148},{"DownloadCount":2404,"UnixTimestamp":1664916551},{"DownloadCount":2400,"UnixTimestamp":1664843727},{"DownloadCount":2396,"UnixTimestamp":1664777099},{"DownloadCount":2392,"UnixTimestamp":1664707436},{"DownloadCount":2388,"UnixTimestamp":1664606000},{"DownloadCount":2384,"UnixTimestamp":1664542144},{"DownloadCount":2379,"UnixTimestamp":1664498023},{"DownloadCount":2375,"UnixTimestamp":1664479711},{"DownloadCount":2369,"UnixTimestamp":1664435563},{"DownloadCount":2363,"UnixTimestamp":1664386618},{"DownloadCount":2359,"UnixTimestamp":1664308060},{"DownloadCount":2354,"UnixTimestamp":1664235233},{"DownloadCount":2350,"UnixTimestamp":1664206320},{"DownloadCount":2344,"UnixTimestamp":1664175031},{"DownloadCount":2340,"UnixTimestamp":1664095009},{"DownloadCount":2336,"UnixTimestamp":1664049726},{"DownloadCount":2332,"UnixTimestamp":1664013270},{"DownloadCount":2328,"UnixTimestamp":1663929433},{"DownloadCount":2324,"UnixTimestamp":1663805537},{"DownloadCount":2320,"UnixTimestamp":1663740475},{"DownloadCount":2315,"UnixTimestamp":1663695153},{"DownloadCount":2309,"UnixTimestamp":1663603877},{"DownloadCount":2304,"UnixTimestamp":1663531647},{"DownloadCount":2299,"UnixTimestamp":1663491311},{"DownloadCount":2294,"UnixTimestamp":1663426382},{"DownloadCount":2290,"UnixTimestamp":1663392987},{"DownloadCount":2286,"UnixTimestamp":1663362719},{"DownloadCount":2281,"UnixTimestamp":1663270798},{"DownloadCount":2277,"UnixTimestamp":1663190776},{"DownloadCount":2272,"UnixTimestamp":1663077919},{"DownloadCount":2268,"UnixTimestamp":1662981016},{"DownloadCount":2260,"UnixTimestamp":1662932033},{"DownloadCount":2254,"UnixTimestamp":1662871392},{"DownloadCount":2249,"UnixTimestamp":1662786866},{"DownloadCount":2245,"UnixTimestamp":1662745172},{"DownloadCount":2241,"UnixTimestamp":1662698722},{"DownloadCount":2237,"UnixTimestamp":1662612638},{"DownloadCount":2232,"UnixTimestamp":1662460196},{"DownloadCount":2227,"UnixTimestamp":1662358731},{"DownloadCount":2221,"UnixTimestamp":1662307777},{"DownloadCount":2217,"UnixTimestamp":1662198393},{"DownloadCount":2210,"UnixTimestamp":1662154945},{"DownloadCount":2205,"UnixTimestamp":1662106239},{"DownloadCount":2201,"UnixTimestamp":1662033613},{"DownloadCount":2197,"UnixTimestamp":1661971763},{"DownloadCount":2193,"UnixTimestamp":1661898630},{"DownloadCount":2188,"UnixTimestamp":1661857029},{"DownloadCount":2184,"UnixTimestamp":1661792211},{"DownloadCount":2179,"UnixTimestamp":1661730174},{"DownloadCount":2177,"UnixTimestamp":1661667216},{"DownloadCount":2173,"UnixTimestamp":1661627276},{"DownloadCount":2169,"UnixTimestamp":1661598485},{"DownloadCount":2165,"UnixTimestamp":1661541081},{"DownloadCount":2160,"UnixTimestamp":1661497291},{"DownloadCount":2153,"UnixTimestamp":1661448548},{"DownloadCount":2147,"UnixTimestamp":1661369090},{"DownloadCount":2143,"UnixTimestamp":1661320154},{"DownloadCount":2138,"UnixTimestamp":1661274707},{"DownloadCount":2134,"UnixTimestamp":1661238308},{"DownloadCount":2129,"UnixTimestamp":1661214512},{"DownloadCount":2124,"UnixTimestamp":1661144770},{"DownloadCount":2119,"UnixTimestamp":1661072496},{"DownloadCount":2114,"UnixTimestamp":1661000039},{"DownloadCount":2109,"UnixTimestamp":1660920627},{"DownloadCount":2105,"UnixTimestamp":1660830701},{"DownloadCount":2100,"UnixTimestamp":1660748252},{"DownloadCount":2096,"UnixTimestamp":1660649447},{"DownloadCount":2092,"UnixTimestamp":1660577178},{"DownloadCount":2088,"UnixTimestamp":1660533016},{"DownloadCount":2084,"UnixTimestamp":1660400647},{"DownloadCount":2080,"UnixTimestamp":1660346801},{"DownloadCount":2076,"UnixTimestamp":1660297186},{"DownloadCount":2072,"UnixTimestamp":1660238687},{"DownloadCount":2068,"UnixTimestamp":1660178634},{"DownloadCount":2068,"UnixTimestamp":1660178634},{"DownloadCount":2061,"UnixTimestamp":1660098927},{"DownloadCount":2057,"UnixTimestamp":1660004702},{"DownloadCount":2053,"UnixTimestamp":1659902989},{"DownloadCount":2049,"UnixTimestamp":1659867344},{"DownloadCount":2045,"UnixTimestamp":1659754244},{"DownloadCount":2041,"UnixTimestamp":1659701774},{"DownloadCount":2037,"UnixTimestamp":1659658911},{"DownloadCount":2033,"UnixTimestamp":1659560544},{"DownloadCount":2033,"UnixTimestamp":1659560544},{"DownloadCount":2017,"UnixTimestamp":1659435751},{"DownloadCount":2024,"UnixTimestamp":1659368445},{"DownloadCount":2020,"UnixTimestamp":1659263188},{"DownloadCount":2016,"UnixTimestamp":1659180094},{"DownloadCount":2010,"UnixTimestamp":1659102683},{"DownloadCount":2010,"UnixTimestamp":1659059160},{"DownloadCount":2006,"UnixTimestamp":1658969582},{"DownloadCount":2002,"UnixTimestamp":1658880667},{"DownloadCount":1998,"UnixTimestamp":1658781816},{"DownloadCount":1994,"UnixTimestamp":1658702531},{"DownloadCount":1989,"UnixTimestamp":1658641853},{"DownloadCount":1984,"UnixTimestamp":1658516917},{"DownloadCount":1980,"UnixTimestamp":1658390654},{"DownloadCount":1980,"UnixTimestamp":1658390654},{"DownloadCount":1972,"UnixTimestamp":1658157214},{"DownloadCount":1968,"UnixTimestamp":1658069197},{"DownloadCount":1964,"UnixTimestamp":1657976891},{"DownloadCount":1960,"UnixTimestamp":1657853379},{"DownloadCount":1956,"UnixTimestamp":1657750283},{"DownloadCount":1952,"UnixTimestamp":1657625360},{"DownloadCount":1946,"UnixTimestamp":1657564374},{"DownloadCount":1945,"UnixTimestamp":1657502576},{"DownloadCount":1941,"UnixTimestamp":1657438070},{"DownloadCount":1937,"UnixTimestamp":1657396510},{"DownloadCount":1932,"UnixTimestamp":1657330251},{"DownloadCount":1928,"UnixTimestamp":1657255405},{"DownloadCount":1928,"UnixTimestamp":1657255405},{"DownloadCount":1922,"UnixTimestamp":1657142035},{"DownloadCount":1917,"UnixTimestamp":1657065518},{"DownloadCount":1912,"UnixTimestamp":1656988615},{"DownloadCount":1908,"UnixTimestamp":1656922330},{"DownloadCount":1904,"UnixTimestamp":1656868389},{"DownloadCount":1900,"UnixTimestamp":1656738005},{"DownloadCount":1895,"UnixTimestamp":1656612088},{"DownloadCount":1891,"UnixTimestamp":1656490741},{"DownloadCount":1891,"UnixTimestamp":1656490741},{"DownloadCount":1884,"UnixTimestamp":1656285226},{"DownloadCount":1883,"UnixTimestamp":1656248749},{"DownloadCount":1883,"UnixTimestamp":1656248749},{"DownloadCount":1876,"UnixTimestamp":1656107375},{"DownloadCount":1872,"UnixTimestamp":1655972482},{"DownloadCount":1868,"UnixTimestamp":1655815480},{"DownloadCount":1863,"UnixTimestamp":1655768884},{"DownloadCount":1859,"UnixTimestamp":1655603867},{"DownloadCount":1855,"UnixTimestamp":1655413829},{"DownloadCount":1848,"UnixTimestamp":1655200993},{"DownloadCount":1848,"UnixTimestamp":1655129013},{"DownloadCount":1842,"UnixTimestamp":1655034521},{"DownloadCount":1837,"UnixTimestamp":1654961772},{"DownloadCount":1832,"UnixTimestamp":1654926006},{"DownloadCount":1828,"UnixTimestamp":1654889646},{"DownloadCount":1824,"UnixTimestamp":1654839969},{"DownloadCount":1820,"UnixTimestamp":1654739203},{"DownloadCount":1816,"UnixTimestamp":1654658339},{"DownloadCount":1812,"UnixTimestamp":1654516806},{"DownloadCount":1808,"UnixTimestamp":1654412110},{"DownloadCount":1804,"UnixTimestamp":1654358041},{"DownloadCount":1800,"UnixTimestamp":1654294251},{"DownloadCount":1796,"UnixTimestamp":1654199863},{"DownloadCount":1792,"UnixTimestamp":1654076894},{"DownloadCount":1788,"UnixTimestamp":1653927818},{"DownloadCount":1784,"UnixTimestamp":1653862398},{"DownloadCount":1780,"UnixTimestamp":1653810946},{"DownloadCount":1776,"UnixTimestamp":1653763342},{"DownloadCount":1771,"UnixTimestamp":1653723063},{"DownloadCount":1767,"UnixTimestamp":1653676668},{"DownloadCount":1762,"UnixTimestamp":1653601837},{"DownloadCount":1758,"UnixTimestamp":1653555514},{"DownloadCount":1753,"UnixTimestamp":1653519828},{"DownloadCount":1749,"UnixTimestamp":1653427804},{"DownloadCount":1744,"UnixTimestamp":1653292550},{"DownloadCount":1740,"UnixTimestamp":1653207861},{"DownloadCount":1740,"UnixTimestamp":1653207861},{"DownloadCount":1733,"UnixTimestamp":1653107991},{"DownloadCount":1729,"UnixTimestamp":1653014898},{"DownloadCount":1725,"UnixTimestamp":1652935786},{"DownloadCount":1721,"UnixTimestamp":1652803588},{"DownloadCount":1716,"UnixTimestamp":1652665566},{"DownloadCount":1712,"UnixTimestamp":1652559555},{"DownloadCount":1708,"UnixTimestamp":1652482179},{"DownloadCount":1704,"UnixTimestamp":1652331629},{"DownloadCount":1700,"UnixTimestamp":1652237262},{"DownloadCount":1696,"UnixTimestamp":1652185368},{"DownloadCount":1692,"UnixTimestamp":1652086036},{"DownloadCount":1688,"UnixTimestamp":1652034516},{"DownloadCount":1684,"UnixTimestamp":1652000486},{"DownloadCount":1678,"UnixTimestamp":1651919042},{"DownloadCount":1671,"UnixTimestamp":1651839775},{"DownloadCount":1666,"UnixTimestamp":1651810910},{"DownloadCount":1662,"UnixTimestamp":1651700046},{"DownloadCount":1658,"UnixTimestamp":1651607309},{"DownloadCount":1654,"UnixTimestamp":1651512993},{"DownloadCount":1650,"UnixTimestamp":1651419021},{"DownloadCount":1646,"UnixTimestamp":1651365780},{"DownloadCount":1642,"UnixTimestamp":1651245350},{"DownloadCount":1638,"UnixTimestamp":1651162174},{"DownloadCount":1634,"UnixTimestamp":1651002712},{"DownloadCount":1629,"UnixTimestamp":1650939790},{"DownloadCount":1624,"UnixTimestamp":1650883308},{"DownloadCount":1619,"UnixTimestamp":1650828243},{"DownloadCount":1615,"UnixTimestamp":1650780694},{"DownloadCount":1611,"UnixTimestamp":1650680230},{"DownloadCount":1607,"UnixTimestamp":1650620111},{"DownloadCount":1603,"UnixTimestamp":1650574768},{"DownloadCount":1599,"UnixTimestamp":1650454414},{"DownloadCount":1595,"UnixTimestamp":1650365740},{"DownloadCount":1591,"UnixTimestamp":1650289295},{"DownloadCount":1587,"UnixTimestamp":1650252536},{"DownloadCount":1583,"UnixTimestamp":1650222778},{"DownloadCount":1579,"UnixTimestamp":1650190039},{"DownloadCount":1574,"UnixTimestamp":1650107861},{"DownloadCount":1570,"UnixTimestamp":1650065251},{"DownloadCount":1568,"UnixTimestamp":1650002519},{"DownloadCount":1564,"UnixTimestamp":1649949400},{"DownloadCount":1559,"UnixTimestamp":1649883441},{"DownloadCount":1555,"UnixTimestamp":1649818342},{"DownloadCount":1551,"UnixTimestamp":1649739761},{"DownloadCount":1547,"UnixTimestamp":1649667048},{"DownloadCount":1543,"UnixTimestamp":1649586124},{"DownloadCount":1537,"UnixTimestamp":1649513134},{"DownloadCount":1533,"UnixTimestamp":1649479448},{"DownloadCount":1529,"UnixTimestamp":1649411240},{"DownloadCount":1525,"UnixTimestamp":1649338827},{"DownloadCount":1521,"UnixTimestamp":1649236281},{"DownloadCount":1517,"UnixTimestamp":1649103433},{"DownloadCount":1512,"UnixTimestamp":1649007217},{"DownloadCount":1508,"UnixTimestamp":1648911336},{"DownloadCount":1504,"UnixTimestamp":1648815935},{"DownloadCount":1500,"UnixTimestamp":1648699125},{"DownloadCount":1496,"UnixTimestamp":1648639319},{"DownloadCount":1492,"UnixTimestamp":1648585599},{"DownloadCount":1488,"UnixTimestamp":1648463437},{"DownloadCount":1484,"UnixTimestamp":1648340673},{"DownloadCount":1480,"UnixTimestamp":1648287387},{"DownloadCount":1475,"UnixTimestamp":1648068074},{"DownloadCount":1471,"UnixTimestamp":1647972776},{"DownloadCount":1467,"UnixTimestamp":1647836112},{"DownloadCount":1463,"UnixTimestamp":1647755708},{"DownloadCount":1459,"UnixTimestamp":1647715588},{"DownloadCount":1454,"UnixTimestamp":1647645526},{"DownloadCount":1449,"UnixTimestamp":1647596711},{"DownloadCount":1445,"UnixTimestamp":1647514898},{"DownloadCount":1441,"UnixTimestamp":1647467532},{"DownloadCount":1437,"UnixTimestamp":1647392770},{"DownloadCount":1437,"UnixTimestamp":1647392770},{"DownloadCount":1430,"UnixTimestamp":1647177544},{"DownloadCount":1426,"UnixTimestamp":1647139293},{"DownloadCount":1422,"UnixTimestamp":1647090290},{"DownloadCount":1418,"UnixTimestamp":1647010056},{"DownloadCount":1414,"UnixTimestamp":1646860477},{"DownloadCount":1410,"UnixTimestamp":1646711438},{"DownloadCount":1406,"UnixTimestamp":1646605206},{"DownloadCount":1402,"UnixTimestamp":1646559355},{"DownloadCount":1398,"UnixTimestamp":1646485331},{"DownloadCount":1394,"UnixTimestamp":1646373659},{"DownloadCount":1390,"UnixTimestamp":1646291690},{"DownloadCount":1386,"UnixTimestamp":1646144879},{"DownloadCount":1382,"UnixTimestamp":1646033208},{"DownloadCount":1378,"UnixTimestamp":1645935771},{"DownloadCount":1374,"UnixTimestamp":1645907304},{"DownloadCount":1370,"UnixTimestamp":1645823126},{"DownloadCount":1366,"UnixTimestamp":1645750862},{"DownloadCount":1362,"UnixTimestamp":1645641057},{"DownloadCount":1357,"UnixTimestamp":1645590408},{"DownloadCount":1353,"UnixTimestamp":1645517778},{"DownloadCount":1349,"UnixTimestamp":1645463001},{"DownloadCount":1345,"UnixTimestamp":1645387969},{"DownloadCount":1341,"UnixTimestamp":1645281600},{"DownloadCount":1337,"UnixTimestamp":1645198273},{"DownloadCount":1333,"UnixTimestamp":1645139978},{"DownloadCount":1329,"UnixTimestamp":1645086246},{"DownloadCount":1325,"UnixTimestamp":1645005469},{"DownloadCount":1321,"UnixTimestamp":1644949585},{"DownloadCount":1317,"UnixTimestamp":1644875612},{"DownloadCount":1313,"UnixTimestamp":1644832618},{"DownloadCount":1309,"UnixTimestamp":1644794372},{"DownloadCount":1305,"UnixTimestamp":1644726701},{"DownloadCount":1301,"UnixTimestamp":1644667421},{"DownloadCount":1295,"UnixTimestamp":1644646814},{"DownloadCount":1291,"UnixTimestamp":1644584606},{"DownloadCount":1287,"UnixTimestamp":1644493087},{"DownloadCount":1283,"UnixTimestamp":1644453346},{"DownloadCount":1279,"UnixTimestamp":1644405290},{"DownloadCount":1274,"UnixTimestamp":1644371039},{"DownloadCount":1270,"UnixTimestamp":1644295152},{"DownloadCount":1266,"UnixTimestamp":1644265511},{"DownloadCount":1261,"UnixTimestamp":1644185938},{"DownloadCount":1254,"UnixTimestamp":1644150846},{"DownloadCount":1250,"UnixTimestamp":1644110031},{"DownloadCount":1246,"UnixTimestamp":1644064902},{"DownloadCount":1242,"UnixTimestamp":1644026412},{"DownloadCount":1237,"UnixTimestamp":1643988308},{"DownloadCount":1233,"UnixTimestamp":1643946651},{"DownloadCount":1229,"UnixTimestamp":1643900475},{"DownloadCount":1225,"UnixTimestamp":1643871107},{"DownloadCount":1220,"UnixTimestamp":1643840784},{"DownloadCount":1215,"UnixTimestamp":1643768120},{"DownloadCount":1211,"UnixTimestamp":1643715031},{"DownloadCount":1207,"UnixTimestamp":1643648259},{"DownloadCount":1203,"UnixTimestamp":1643549308},{"DownloadCount":1198,"UnixTimestamp":1643484718},{"DownloadCount":1194,"UnixTimestamp":1643408744},{"DownloadCount":1190,"UnixTimestamp":1643300690},{"DownloadCount":1186,"UnixTimestamp":1643231069},{"DownloadCount":1181,"UnixTimestamp":1643131572},{"DownloadCount":1177,"UnixTimestamp":1643047606},{"DownloadCount":1173,"UnixTimestamp":1642981469},{"DownloadCount":1169,"UnixTimestamp":1642961764},{"DownloadCount":1164,"UnixTimestamp":1642920581},{"DownloadCount":1154,"UnixTimestamp":1642821764},{"DownloadCount":1148,"UnixTimestamp":1642789099},{"DownloadCount":1144,"UnixTimestamp":1642732677},{"DownloadCount":1140,"UnixTimestamp":1642642976},{"DownloadCount":1136,"UnixTimestamp":1642588899},{"DownloadCount":1132,"UnixTimestamp":1642556380},{"DownloadCount":1128,"UnixTimestamp":1642539027},{"DownloadCount":1124,"UnixTimestamp":1642527412},{"DownloadCount":1118,"UnixTimestamp":1642514276},{"DownloadCount":1114,"UnixTimestamp":1642480505},{"DownloadCount":1110,"UnixTimestamp":1642459801},{"DownloadCount":1106,"UnixTimestamp":1642441495},{"DownloadCount":1102,"UnixTimestamp":1642409879},{"DownloadCount":1098,"UnixTimestamp":1642361967},{"DownloadCount":1094,"UnixTimestamp":1642341943},{"DownloadCount":1090,"UnixTimestamp":1642310609},{"DownloadCount":1086,"UnixTimestamp":1642251917},{"DownloadCount":1082,"UnixTimestamp":1642209520},{"DownloadCount":1077,"UnixTimestamp":1642144672},{"DownloadCount":1073,"UnixTimestamp":1642069429},{"DownloadCount":1069,"UnixTimestamp":1642029446},{"DownloadCount":1065,"UnixTimestamp":1641958733},{"DownloadCount":1061,"UnixTimestamp":1641915058},{"DownloadCount":1056,"UnixTimestamp":1641862259},{"DownloadCount":1052,"UnixTimestamp":1641821737},{"DownloadCount":1047,"UnixTimestamp":1641732340},{"DownloadCount":1043,"UnixTimestamp":1641692873},{"DownloadCount":1037,"UnixTimestamp":1641650839},{"DownloadCount":1033,"UnixTimestamp":1641606647},{"DownloadCount":1028,"UnixTimestamp":1641570095},{"DownloadCount":1024,"UnixTimestamp":1641554332},{"DownloadCount":1019,"UnixTimestamp":1641518863},{"DownloadCount":1014,"UnixTimestamp":1641496791},{"DownloadCount":1010,"UnixTimestamp":1641485805},{"DownloadCount":1006,"UnixTimestamp":1641463907},{"DownloadCount":1001,"UnixTimestamp":1641429600},{"DownloadCount":997,"UnixTimestamp":1641381570},{"DownloadCount":993,"UnixTimestamp":1641324875},{"DownloadCount":989,"UnixTimestamp":1641265193},{"DownloadCount":984,"UnixTimestamp":1641205945},{"DownloadCount":980,"UnixTimestamp":1641181754},{"DownloadCount":975,"UnixTimestamp":1641158636},{"DownloadCount":970,"UnixTimestamp":1641142802},{"DownloadCount":963,"UnixTimestamp":1641104673},{"DownloadCount":958,"UnixTimestamp":1641075046},{"DownloadCount":953,"UnixTimestamp":1641057302},{"DownloadCount":947,"UnixTimestamp":1641019814},{"DownloadCount":943,"UnixTimestamp":1640979791},{"DownloadCount":939,"UnixTimestamp":1640905001},{"DownloadCount":935,"UnixTimestamp":1640847640},{"DownloadCount":931,"UnixTimestamp":1640810273},{"DownloadCount":927,"UnixTimestamp":1640760193},{"DownloadCount":923,"UnixTimestamp":1640730459},{"DownloadCount":919,"UnixTimestamp":1640704658},{"DownloadCount":915,"UnixTimestamp":1640657352},{"DownloadCount":909,"UnixTimestamp":1640627917},{"DownloadCount":905,"UnixTimestamp":1640592950},{"DownloadCount":900,"UnixTimestamp":1640563779},{"DownloadCount":896,"UnixTimestamp":1640530621},{"DownloadCount":892,"UnixTimestamp":1640478491},{"DownloadCount":888,"UnixTimestamp":1640454338},{"DownloadCount":883,"UnixTimestamp":1640381447},{"DownloadCount":879,"UnixTimestamp":1640306998},{"DownloadCount":875,"UnixTimestamp":1640225410},{"DownloadCount":871,"UnixTimestamp":1640182427},{"DownloadCount":867,"UnixTimestamp":1640137552},{"DownloadCount":863,"UnixTimestamp":1640099931},{"DownloadCount":859,"UnixTimestamp":1640040432},{"DownloadCount":855,"UnixTimestamp":1639983668},{"DownloadCount":851,"UnixTimestamp":1639937270},{"DownloadCount":846,"UnixTimestamp":1639890197},{"DownloadCount":842,"UnixTimestamp":1639858288},{"DownloadCount":838,"UnixTimestamp":1639765759},{"DownloadCount":834,"UnixTimestamp":1639680090},{"DownloadCount":829,"UnixTimestamp":1639615423},{"DownloadCount":825,"UnixTimestamp":1639552810},{"DownloadCount":821,"UnixTimestamp":1639495827},{"DownloadCount":816,"UnixTimestamp":1639421686},{"DownloadCount":812,"UnixTimestamp":1639349915},{"DownloadCount":807,"UnixTimestamp":1639267251},{"DownloadCount":803,"UnixTimestamp":1639192252},{"DownloadCount":799,"UnixTimestamp":1639137481},{"DownloadCount":795,"UnixTimestamp":1639094366},{"DownloadCount":791,"UnixTimestamp":1639058957},{"DownloadCount":787,"UnixTimestamp":1639027267},{"DownloadCount":783,"UnixTimestamp":1639008608},{"DownloadCount":779,"UnixTimestamp":1638968079},{"DownloadCount":775,"UnixTimestamp":1638894641},{"DownloadCount":771,"UnixTimestamp":1638837735},{"DownloadCount":767,"UnixTimestamp":1638784830},{"DownloadCount":763,"UnixTimestamp":1638755495},{"DownloadCount":759,"UnixTimestamp":1638733173},{"DownloadCount":755,"UnixTimestamp":1638725867},{"DownloadCount":751,"UnixTimestamp":1638703280},{"DownloadCount":747,"UnixTimestamp":1638679581},{"DownloadCount":742,"UnixTimestamp":1638663068},{"DownloadCount":737,"UnixTimestamp":1638642145},{"DownloadCount":731,"UnixTimestamp":1638621625},{"DownloadCount":727,"UnixTimestamp":1638600787},{"DownloadCount":722,"UnixTimestamp":1638577172},{"DownloadCount":718,"UnixTimestamp":1638568444},{"DownloadCount":712,"UnixTimestamp":1638516941},{"DownloadCount":708,"UnixTimestamp":1638473042},{"DownloadCount":704,"UnixTimestamp":1638389515},{"DownloadCount":700,"UnixTimestamp":1638289781},{"DownloadCount":696,"UnixTimestamp":1638227504},{"DownloadCount":692,"UnixTimestamp":1638161366},{"DownloadCount":687,"UnixTimestamp":1638114813},{"DownloadCount":683,"UnixTimestamp":1638065115},{"DownloadCount":675,"UnixTimestamp":1638038263},{"DownloadCount":670,"UnixTimestamp":1637983313},{"DownloadCount":666,"UnixTimestamp":1637921227},{"DownloadCount":662,"UnixTimestamp":1637867020},{"DownloadCount":658,"UnixTimestamp":1637837272},{"DownloadCount":654,"UnixTimestamp":1637817056},{"DownloadCount":650,"UnixTimestamp":1637796415},{"DownloadCount":646,"UnixTimestamp":1637750981},{"DownloadCount":642,"UnixTimestamp":1637706780},{"DownloadCount":638,"UnixTimestamp":1637639814},{"DownloadCount":634,"UnixTimestamp":1637611632},{"DownloadCount":630,"UnixTimestamp":1637587818},{"DownloadCount":626,"UnixTimestamp":1637552365},{"DownloadCount":621,"UnixTimestamp":1637518443},{"DownloadCount":616,"UnixTimestamp":1637486150},{"DownloadCount":612,"UnixTimestamp":1637471768},{"DownloadCount":608,"UnixTimestamp":1637447462},{"DownloadCount":604,"UnixTimestamp":1637423159},{"DownloadCount":600,"UnixTimestamp":1637400653},{"DownloadCount":596,"UnixTimestamp":1637380076},{"DownloadCount":592,"UnixTimestamp":1637322476},{"DownloadCount":588,"UnixTimestamp":1637255757},{"DownloadCount":584,"UnixTimestamp":1637209169},{"DownloadCount":580,"UnixTimestamp":1637104721},{"DownloadCount":575,"UnixTimestamp":1637056514},{"DownloadCount":571,"UnixTimestamp":1637026621},{"DownloadCount":567,"UnixTimestamp":1636979059},{"DownloadCount":562,"UnixTimestamp":1636929383},{"DownloadCount":558,"UnixTimestamp":1636909527},{"DownloadCount":554,"UnixTimestamp":1636856704},{"DownloadCount":550,"UnixTimestamp":1636829372},{"DownloadCount":546,"UnixTimestamp":1636804721},{"DownloadCount":541,"UnixTimestamp":1636763363},{"DownloadCount":536,"UnixTimestamp":1636748833},{"DownloadCount":532,"UnixTimestamp":1636718884},{"DownloadCount":528,"UnixTimestamp":1636684752},{"DownloadCount":524,"UnixTimestamp":1636655902},{"DownloadCount":520,"UnixTimestamp":1636624441},{"DownloadCount":516,"UnixTimestamp":1636576785},{"DownloadCount":512,"UnixTimestamp":1636540295},{"DownloadCount":508,"UnixTimestamp":1636504888},{"DownloadCount":504,"UnixTimestamp":1636484222},{"DownloadCount":500,"UnixTimestamp":1636437335},{"DownloadCount":495,"UnixTimestamp":1636388878},{"DownloadCount":490,"UnixTimestamp":1636357019},{"DownloadCount":485,"UnixTimestamp":1636337660},{"DownloadCount":481,"UnixTimestamp":1636316595},{"DownloadCount":477,"UnixTimestamp":1636288750},{"DownloadCount":472,"UnixTimestamp":1636249284},{"DownloadCount":468,"UnixTimestamp":1636234124},{"DownloadCount":463,"UnixTimestamp":1636225947},{"DownloadCount":459,"UnixTimestamp":1636185081},{"DownloadCount":455,"UnixTimestamp":1636168315},{"DownloadCount":448,"UnixTimestamp":1636149797},{"DownloadCount":444,"UnixTimestamp":1636134537},{"DownloadCount":440,"UnixTimestamp":1636096541},{"DownloadCount":436,"UnixTimestamp":1636060054},{"DownloadCount":432,"UnixTimestamp":1636042391},{"DownloadCount":428,"UnixTimestamp":1635995129},{"DownloadCount":424,"UnixTimestamp":1635981344},{"DownloadCount":420,"UnixTimestamp":1635971601},{"DownloadCount":416,"UnixTimestamp":1635960060},{"DownloadCount":412,"UnixTimestamp":1635940424},{"DownloadCount":408,"UnixTimestamp":1635913170},{"DownloadCount":403,"UnixTimestamp":1635875232},{"DownloadCount":399,"UnixTimestamp":1635838638},{"DownloadCount":395,"UnixTimestamp":1635809248},{"DownloadCount":391,"UnixTimestamp":1635794606},{"DownloadCount":386,"UnixTimestamp":1635763356},{"DownloadCount":382,"UnixTimestamp":1635731032},{"DownloadCount":378,"UnixTimestamp":1635712171},{"DownloadCount":373,"UnixTimestamp":1635689806},{"DownloadCount":369,"UnixTimestamp":1635678853},{"DownloadCount":365,"UnixTimestamp":1635666335},{"DownloadCount":360,"UnixTimestamp":1635649130},{"DownloadCount":356,"UnixTimestamp":1635635664},{"DownloadCount":351,"UnixTimestamp":1635622086},{"DownloadCount":347,"UnixTimestamp":1635616335},{"DownloadCount":342,"UnixTimestamp":1635606258},{"DownloadCount":337,"UnixTimestamp":1635582668},{"DownloadCount":331,"UnixTimestamp":1635543748},{"DownloadCount":327,"UnixTimestamp":1635504351},{"DownloadCount":322,"UnixTimestamp":1635464246},{"DownloadCount":318,"UnixTimestamp":1635435863},{"DownloadCount":314,"UnixTimestamp":1635410933},{"DownloadCount":310,"UnixTimestamp":1635399790},{"DownloadCount":305,"UnixTimestamp":1635371684},{"DownloadCount":300,"UnixTimestamp":1635351780},{"DownloadCount":295,"UnixTimestamp":1635329037},{"DownloadCount":291,"UnixTimestamp":1635305438},{"DownloadCount":286,"UnixTimestamp":1635290181},{"DownloadCount":282,"UnixTimestamp":1635281741},{"DownloadCount":278,"UnixTimestamp":1635276130},{"DownloadCount":274,"UnixTimestamp":1635264267},{"DownloadCount":269,"UnixTimestamp":1635246415},{"DownloadCount":264,"UnixTimestamp":1635231749},{"DownloadCount":260,"UnixTimestamp":1635216121},{"DownloadCount":254,"UnixTimestamp":1635202625},{"DownloadCount":250,"UnixTimestamp":1635198176},{"DownloadCount":245,"UnixTimestamp":1635195561},{"DownloadCount":240,"UnixTimestamp":1635189163},{"DownloadCount":235,"UnixTimestamp":1635180936},{"DownloadCount":230,"UnixTimestamp":1635173281},{"DownloadCount":224,"UnixTimestamp":1635158128},{"DownloadCount":224,"UnixTimestamp":1635158128}]